<?xml version="1.0" encoding="UTF-8" standalone="no"?>
<hotlinks>
    <hotlink page="1" clickSound="true" pagewidth="874" x="71" y="1146" width="80" height="86" color="#f2fa13" fontColor="#000000" fontSize="#000000" opacity="0.00" rolloverOpacity="0.00" rolloverText="Click for link !" rolloverColor="#f8ff0f" destination="http://www.lesvitrinesdevence.fr" target="_blank"></hotlink>
    <hotlink page="1" clickSound="true" pagewidth="874" x="633" y="983" width="231" height="204" color="#f2fa13" fontColor="#000000" fontSize="#000000" opacity="0.00" rolloverOpacity="0.00" rolloverText="Click for link !" rolloverColor="#f8ff0f" destination="http://www.lesvitrinesdevence.fr/Members" target="_blank"></hotlink>
    <hotlink page="4" clickSound="true" pagewidth="874" x="463" y="681" width="113" height="150" color="#f2fa13" fontColor="#000000" fontSize="#000000" opacity="0.00" rolloverOpacity="0.00" rolloverText="Click for link !" rolloverColor="#f8ff0f" destination="http://www.quickguidetocity.com/magazines/vence/Fashion" target="_blank"></hotlink>
    <hotlink page="4" clickSound="true" pagewidth="874" x="578" y="682" width="113" height="156" color="#f2fa13" fontColor="#000000" fontSize="#000000" opacity="0.00" rolloverOpacity="0.00" rolloverText="Click for link !" rolloverColor="#f8ff0f" destination="http://www.quickguidetocity.com/magazines/vence/Souvenirs" target="_blank"></hotlink>
    <hotlink page="4" clickSound="true" pagewidth="874" x="690" y="682" width="131" height="150" color="#f2fa13" fontColor="#000000" fontSize="#000000" opacity="0.00" rolloverOpacity="0.00" rolloverText="Click for link !" rolloverColor="#f8ff0f" destination="http://www.quickguidetocity.com/magazines/vence/Delicatessen" target="_blank"></hotlink>
    <hotlink page="4" clickSound="true" pagewidth="874" x="469" y="850" width="120" height="156" color="#f2fa13" fontColor="#000000" fontSize="#000000" opacity="0.00" rolloverOpacity="0.00" rolloverText="Click for link !" rolloverColor="#f8ff0f" destination="http://www.quickguidetocity.com/magazines/vence/Hotels" target="_blank"></hotlink>
    <hotlink page="4" clickSound="true" pagewidth="874" x="585" y="848" width="113" height="159" color="#f2fa13" fontColor="#000000" fontSize="#000000" opacity="0.00" rolloverOpacity="0.00" rolloverText="Click for link !" rolloverColor="#f8ff0f" destination="http://www.quickguidetocity.com/magazines/vence/Guesthouses" target="_blank"></hotlink>
    <hotlink page="4" clickSound="true" pagewidth="874" x="682" y="1033" width="136" height="143" color="#f2fa13" fontColor="#000000" fontSize="#000000" opacity="0.00" rolloverOpacity="0.00" rolloverText="Click for link !" rolloverColor="#f8ff0f" destination="http://www.quickguidetocity.com/magazines/vence/Restaurants" target="_blank"></hotlink>
    <hotlink page="5" clickSound="true" pagewidth="874" x="680" y="156" width="152" height="147" color="#f2fa13" fontColor="#000000" fontSize="#000000" opacity="0.00" rolloverOpacity="0.00" rolloverText="Click for link !" rolloverColor="#f8ff0f" destination="http://www.quickguidetocity.com/magazines/vence/Cafes" target="_blank"></hotlink>
    <hotlink page="5" clickSound="true" pagewidth="874" x="682" y="337" width="152" height="136" color="#f2fa13" fontColor="#000000" fontSize="#000000" opacity="0.00" rolloverOpacity="0.00" rolloverText="Click for link !" rolloverColor="#f8ff0f" destination="http://www.quickguidetocity.com/magazines/vence/Realestate" target="_blank"></hotlink>
    <hotlink page="5" clickSound="true" pagewidth="874" x="470" y="508" width="116" height="150" color="#f2fa13" fontColor="#000000" fontSize="#000000" opacity="0.00" rolloverOpacity="0.00" rolloverText="Click for link !" rolloverColor="#f8ff0f" destination="http://www.quickguidetocity.com/magazines/vence/Services" target="_blank"></hotlink>
    <hotlink page="5" clickSound="true" pagewidth="874" x="585" y="508" width="115" height="149" color="#f2fa13" fontColor="#000000" fontSize="#000000" opacity="0.00" rolloverOpacity="0.00" rolloverText="Click for link !" rolloverColor="#f8ff0f" destination="http://www.quickguidetocity.com/magazines/vence/Finance" target="_blank"></hotlink>
    <hotlink page="5" clickSound="true" pagewidth="874" x="696" y="510" width="131" height="150" color="#f2fa13" fontColor="#000000" fontSize="#000000" opacity="0.00" rolloverOpacity="0.00" rolloverText="Click for link !" rolloverColor="#f8ff0f" destination="http://www.quickguidetocity.com/magazines/vence/Takeaway" target="_blank"></hotlink>
    <hotlink page="5" clickSound="true" pagewidth="874" x="680" y="684" width="152" height="145" color="#f2fa13" fontColor="#000000" fontSize="#000000" opacity="0.00" rolloverOpacity="0.00" rolloverText="Click for link !" rolloverColor="#f8ff0f" destination="http://www.quickguidetocity.com/magazines/vence/Galleries" target="_blank"></hotlink>
    <hotlink page="5" clickSound="true" pagewidth="874" x="678" y="850" width="161" height="159" color="#f2fa13" fontColor="#000000" fontSize="#000000" opacity="0.00" rolloverOpacity="0.00" rolloverText="Click for link !" rolloverColor="#f8ff0f" destination="http://www.quickguidetocity.com/magazines/vence/Beauty" target="_blank"></hotlink>
    <hotlink page="5" clickSound="true" pagewidth="874" x="678" y="1024" width="158" height="163" color="#f2fa13" fontColor="#000000" fontSize="#000000" opacity="0.00" rolloverOpacity="0.00" rolloverText="Click for link !" rolloverColor="#f8ff0f" destination="http://www.quickguidetocity.com/magazines/vence/Places" target="_blank"></hotlink>
    <hotlink page="9" clickSound="true" pagewidth="874" x="705" y="1035" width="111" height="97" color="#f2fa13" fontColor="#000000" fontSize="#000000" opacity="0.00" rolloverOpacity="0.00" rolloverText="Click for link !" rolloverColor="#f8ff0f" destination="http://www.quickguidetocity.com/magazines/vence/Fashion" target="_blank"></hotlink>
    <hotlink page="11" clickSound="true" pagewidth="874" x="576" y="1055" width="124" height="100" color="#f2fa13" fontColor="#000000" fontSize="#000000" opacity="0.00" rolloverOpacity="0.00" rolloverText="Click for link !" rolloverColor="#f8ff0f" destination="http://www.quickguidetocity.com/magazines/vence/Galleries" target="_blank"></hotlink>
    <hotlink page="13" clickSound="true" pagewidth="874" x="684" y="564" width="138" height="102" color="#f2fa13" fontColor="#000000" fontSize="#000000" opacity="0.00" rolloverOpacity="0.00" rolloverText="Click for link !" rolloverColor="#f8ff0f" destination="http://www.quickguidetocity.com/magazines/vence/Places" target="_blank"></hotlink>
    <hotlink page="4" clickSound="true" pagewidth="874" x="699" y="853" width="107" height="147" color="#f2fa13" fontColor="#000000" fontSize="#000000" opacity="0.00" rolloverOpacity="0.00" rolloverText="Click for link !" rolloverColor="#f8ff0f" destination="http://www.camping-domainedelabergerie.com" target="_blank"></hotlink>
    <hotlink page="7" clickSound="true" pagewidth="874" x="375" y="1119" width="118" height="84" color="#f2fa13" fontColor="#000000" fontSize="#000000" opacity="0.00" rolloverOpacity="0.00" rolloverText="Back to overview !" rolloverColor="#f8ff0f" destination="page:4"></hotlink>
    <hotlink page="9" clickSound="true" pagewidth="874" x="373" y="1114" width="145" height="93" color="#f2fa13" fontColor="#000000" fontSize="#000000" opacity="0.00" rolloverOpacity="0.00" rolloverText="Back to overview !" rolloverColor="#f8ff0f" destination="page:4"></hotlink>
    <hotlink page="11" clickSound="true" pagewidth="874" x="360" y="1121" width="154" height="86" color="#f2fa13" fontColor="#000000" fontSize="#000000" opacity="0.00" rolloverOpacity="0.00" rolloverText="Back to overview !" rolloverColor="#f8ff0f" destination="page:4"></hotlink>
    <hotlink page="13" clickSound="true" pagewidth="874" x="384" y="1125" width="115" height="86" color="#f2fa13" fontColor="#000000" fontSize="#000000" opacity="0.00" rolloverOpacity="0.00" rolloverText="Back to overview !" rolloverColor="#f8ff0f" destination="page:4"></hotlink>
    <hotlink page="15" clickSound="true" pagewidth="874" x="371" y="1121" width="134" height="86" color="#f2fa13" fontColor="#000000" fontSize="#000000" opacity="0.00" rolloverOpacity="0.00" rolloverText="Back to overview !" rolloverColor="#f8ff0f" destination="page:4"></hotlink>
    <hotlink page="17" clickSound="true" pagewidth="874" x="382" y="1117" width="145" height="86" color="#f2fa13" fontColor="#000000" fontSize="#000000" opacity="0.00" rolloverOpacity="0.00" rolloverText="Back to overview !" rolloverColor="#f8ff0f" destination="page:4"></hotlink>
    <hotlink page="16" clickSound="true" pagewidth="874" x="209" y="365" width="436" height="86" color="#f2fa13" fontColor="#000000" fontSize="#000000" opacity="0.00" rolloverOpacity="0.00" rolloverText="Back to overview !" rolloverColor="#f8ff0f" destination="http://www.ville-vence.fr" target="_blank"></hotlink>
    <hotlink page="18" clickSound="true" pagewidth="874" x="300" y="71" width="260" height="364" color="#f2fa13" fontColor="#000000" fontSize="#000000" opacity="0.00" rolloverOpacity="0.00" rolloverText="Back to overview !" rolloverColor="#f8ff0f" destination="http://www.lesvitrinesdevence.fr/Papier" target="_blank"></hotlink>
    <hotlink page="18" clickSound="true" pagewidth="874" x="273" y="603" width="321" height="179" color="#f2fa13" fontColor="#000000" fontSize="#000000" opacity="0.00" rolloverOpacity="0.00" rolloverText="Send email !" rolloverColor="#f8ff0f" destination="mailto:info@worldondvd.com"></hotlink>
</hotlinks>